头歌答案/时序逻辑电路设计/移位寄存器的应用/lut3/lut3.v
module lut3(
    input    sys_clk,
    input    sys_rst_n,
    input    en,
    input    S,
    input    A,
    input    B,
    input    C,
    output   Z
);

	// 代码量预计6行
    reg [7 : 0] Q;

    assign Z = Q[ {A, B, C} ];

    always @(posedge sys_clk) begin
        if(~sys_rst_n)   Q <= 8'b0;
        else if(en) Q <= {Q[6 : 0], S};
    end

endmodule

头歌答案/时序逻辑电路设计/移位寄存器的应用/lut3/tb_lut3.v
`timescale 1ns/1ns

`define CLK_PERIOD 10

module tb_lut3();

	reg		sys_clk, sys_rst_n;
    reg     en, S;
    reg     A, B, C;
    wire	Z;

    lut3 U0(
        .sys_clk(sys_clk),
        .sys_rst_n(sys_rst_n),
        .en(en),
        .S(S),
        .A(A),
        .B(B),
        .C(C),
        .Z(Z)
    );

    initial begin
    
        sys_clk     <= 1'b0;
        sys_rst_n   <= 1'b0;
        en          <= 1'b0;
        S           <= 1'b1;
        {A, B, C}   <= 3'b000;
        #20;
        sys_rst_n   <= 1'b1;
        en          <= 1'b1;
    
    end
    
    always #(`CLK_PERIOD/2) sys_clk = ~sys_clk;

    int i;
    
    initial begin

    	@(posedge sys_rst_n);

        @(posedge sys_clk);
        S <= 1'b0;
        @(posedge sys_clk);
        S <= 1'b0;
        @(posedge sys_clk);
        S <= 1'b1;
        @(posedge sys_clk);
        S <= 1'b1;
        @(posedge sys_clk);
        S <= 1'b1;
        @(posedge sys_clk);
        S <= 1'b0;
        @(posedge sys_clk);
        S <= 1'b0;
        @(posedge sys_clk);
        en <= 1'b0;
        @(posedge sys_clk);

        for(i = 7; i >= 0; i--) begin
            {A, B, C} = i;
            #5;
        end

        $finish;                
    
    end

    initial begin
    
        $timeformat(-9, 0, "ns", 5);
        $monitor("At time %t: sys_rst_n = %b, en = %b, S = %b, {A, B, C} = %b%b%b, Z = %b", $time, sys_rst_n, en, S, A, B, C, Z);
    
    end

    initial begin

		$dumpfile("waveform.vcd");
		$dumpvars(1, tb_lut3.U0.sys_clk);
		$dumpvars(1, tb_lut3.U0.sys_rst_n);
		$dumpvars(1, tb_lut3.U0.en);
        $dumpvars(1, tb_lut3.U0.S);
        $dumpvars(1, tb_lut3.U0.Q);
        $dumpvars(1, tb_lut3.U0.A);
        $dumpvars(1, tb_lut3.U0.B);
        $dumpvars(1, tb_lut3.U0.C);
        $dumpvars(1, tb_lut3.U0.Z);

    end

endmodule // tb_lut3

头歌答案/时序逻辑电路设计/移位寄存器的应用/lut3/waveform.vcd
$date
	Tue Jan 11 21:17:29 2022
$end
$version
	Icarus Verilog
$end
$timescale
	1ns
$end
$scope module tb_lut3 $end
$scope module U0 $end
$var wire 1 ! sys_clk $end
$upscope $end
$upscope $end
$scope module tb_lut3 $end
$scope module U0 $end
$var wire 1 " sys_rst_n $end
$upscope $end
$upscope $end
$scope module tb_lut3 $end
$scope module U0 $end
$var wire 1 # en $end
$upscope $end
$upscope $end
$scope module tb_lut3 $end
$scope module U0 $end
$var wire 1 $ S $end
$upscope $end
$upscope $end
$scope module tb_lut3 $end
$scope module U0 $end
$var reg 8 % Q [7:0] $end
$upscope $end
$upscope $end
$scope module tb_lut3 $end
$scope module U0 $end
$var wire 1 & A $end
$upscope $end
$upscope $end
$scope module tb_lut3 $end
$scope module U0 $end
$var wire 1 ' B $end
$upscope $end
$upscope $end
$scope module tb_lut3 $end
$scope module U0 $end
$var wire 1 ( C $end
$upscope $end
$upscope $end
$scope module tb_lut3 $end
$scope module U0 $end
$var wire 1 ) Z $end
$upscope $end
$upscope $end
$enddefinitions $end
#0
$dumpvars
x)
0(
0'
0&
bx %
1$
0#
0"
0!
$end
#5
0)
b0 %
1!
#10
0!
#15
1!
#20
1#
1"
0!
#25
1)
b1 %
0$
1!
#30
0!
#35
0)
b10 %
1!
#40
0!
#45
b100 %
1$
1!
#50
0!
#55
1)
b1001 %
1!
#60
0!
#65
b10011 %
1!
#70
0!
#75
0$
b100111 %
1!
#80
0!
#85
0)
b1001110 %
1!
#90
0!
#95
0#
b10011100 %
1!
#100
0!
#105
1&
1)
1'
1(
1!
#110
0)
0(
0!
#115
0'
0)
1(
1!
#120
1)
0(
0!
#125
0&
1'
1)
1(
1!
#130
0(
0!
#135
0)
0'
1(
1!
#140
0(
0!
