头歌答案/时序逻辑电路设计/触发器和寄存器/reg4_struc/dff_syn.v
module dff_syn(
    input   sys_clk,
    input   sys_rst_n,
    input   D,
    output  Q
);

	// 代码量预计5行
    reg Q;

    always @(posedge sys_clk) begin
    
        if (~sys_rst_n) Q <= 0;
        else            Q <= D;
    
    end


endmodule

头歌答案/时序逻辑电路设计/触发器和寄存器/dff_syn/tb_dff_syn.v
`timescale 1ns/1ns

`define CLK_PERIOD 10

module tb_dff_syn();

	reg		sys_clk, sys_rst_n;
    reg		D;
    wire	Q;
    
    dff_syn U0(.sys_clk(sys_clk), .sys_rst_n(sys_rst_n), .D(D), .Q(Q));
    
    always #(`CLK_PERIOD/2) sys_clk = ~sys_clk;

    initial begin
    
        sys_clk     <= 1'b0;
        sys_rst_n   <= 1'b0;
        D           <= 1'b0;
        #20;
        sys_rst_n   <= 1'b1;
    
    end
    
    initial begin

    	repeat(3) @(posedge sys_clk);
        	D <= 1'b1;
        repeat(2) @(posedge sys_clk);
        	D <= 1'b0;
        repeat(3) @(posedge sys_clk);
        	D <= 1'b1;
        repeat(2) @(posedge sys_clk);
            sys_rst_n <= 1'b0;
        repeat(2) @(posedge sys_clk);
            $finish;                
    
    end

    initial begin
    
        $timeformat(-9, 0, "ns", 5);
        $monitor("At time %t: sys_rst_n = %b, D = %b, Q = %b", $time, sys_rst_n, D, Q);
    
    end

    initial begin

		$dumpfile("waveform.vcd");
		$dumpvars(1, tb_dff_syn.U0.sys_clk);
        $dumpvars(1, tb_dff_syn.U0.sys_rst_n);
		$dumpvars(1, tb_dff_syn.U0.D);
		$dumpvars(1, tb_dff_syn.U0.Q);

    end

endmodule // tb_dff_syn

头歌答案/时序逻辑电路设计/触发器和寄存器/dff_syn/waveform.vcd
$date
	Mon Jan 10 11:08:31 2022
$end
$version
	Icarus Verilog
$end
$timescale
	1ns
$end
$scope module tb_dff_syn $end
$scope module U0 $end
$var wire 1 ! sys_clk $end
$upscope $end
$upscope $end
$scope module tb_dff_syn $end
$scope module U0 $end
$var wire 1 " sys_rst_n $end
$upscope $end
$upscope $end
$scope module tb_dff_syn $end
$scope module U0 $end
$var wire 1 # D $end
$upscope $end
$upscope $end
$scope module tb_dff_syn $end
$scope module U0 $end
$var reg 1 $ Q $end
$upscope $end
$upscope $end
$enddefinitions $end
#0
$dumpvars
x$
0#
0"
0!
$end
#5
0$
1!
#10
0!
#15
1!
#20
1"
0!
#25
1#
1!
#30
0!
#35
1$
1!
#40
0!
#45
0#
1!
#50
0!
#55
0$
1!
#60
0!
#65
1!
#70
0!
#75
1#
1!
#80
0!
#85
1$
1!
#90
0!
#95
0"
1!
#100
0!
#105
0$
1!
