头歌答案/硬件描述语言基础/过程块/case1/case1.sv
module case1(
    input [2:0] sel, 
    input [3:0] data0,
    input [3:0] data1,
    input [3:0] data2,
    input [3:0] data3,
    input [3:0] data4,
    input [3:0] data5,
    output[3:0] out
);

	// 代码量预计11行

    reg [3 : 0] out;

	 always@(*)          // 注意不要丢失default语句，以确保生成组合逻辑电路
        case(sel)
            3'b000: out = data0;
            3'b001: out = data1;
            3'b010: out = data2;
            3'b011: out = data3;
            3'b100: out = data4;
            3'b101: out = data5;
            default out = 0;
        endcase

endmodule

头歌答案/硬件描述语言基础/过程块/case1/tb_case1.sv
`timescale 1ns/1ns

module tb_case1();

	logic   	[2 : 0]	sel;
	logic		[3 : 0]	data0, data1, data2, data3, data4, data5;
	logic 		[3 : 0]	out;

	/***Verilog HDL Code***/
	//reg   	[2 : 0]	sel;
	//reg		[3 : 0]	data0, data1, data2, data3, data4, data5;
	//wire 		[3 : 0]	out;

	case1 U0(	.sel		(sel)	, 
				.data0		(data0)	, 
				.data1		(data1)	, 
				.data2		(data2)	, 
				.data3		(data3)	,
				.data4		(data4)	,
				.data5		(data5)	,
				.out 		(out)
			);

	int i;

	initial begin
			data0 = 4'h8;
			data1 = 4'h9;
			data2 = 4'hA;
			data3 = 4'hB;
			data4 = 4'hC;
			data5 = 4'hD;
			for (int i = 0; i < 8; i++) begin
				sel = i;
				#5;
			end
		#5 $finish;
	end

	initial begin
    
        $timeformat(-9, 0, "ns", 5);
        $monitor("At time %t: data0 = 0x%h, data1 = 0x%h, data2 = 0x%h, data3 = 0x%h, data4 = 0x%h, data5 = 0x%h, sel = 0x%h, out = 0x%h", $time, data0, data1, data2, data3, data4, data5, sel, out);
    
    end

    initial begin

		$dumpfile("waveform.vcd");
		$dumpvars(1, tb_case1.U0.data0);
		$dumpvars(1, tb_case1.U0.data1);
		$dumpvars(1, tb_case1.U0.data2);
		$dumpvars(1, tb_case1.U0.data3);
		$dumpvars(1, tb_case1.U0.data4);
		$dumpvars(1, tb_case1.U0.data5);
		$dumpvars(1, tb_case1.U0.sel);
		$dumpvars(1, tb_case1.U0.out);

    end

endmodule // tb_case1

头歌答案/硬件描述语言基础/过程块/case1/waveform.vcd
$date
	Thu Dec 16 21:52:15 2021
$end
$version
	Icarus Verilog
$end
$timescale
	1ns
$end
$scope module tb_case1 $end
$scope module U0 $end
$var wire 4 ! data0 [3:0] $end
$upscope $end
$upscope $end
$scope module tb_case1 $end
$scope module U0 $end
$var wire 4 " data1 [3:0] $end
$upscope $end
$upscope $end
$scope module tb_case1 $end
$scope module U0 $end
$var wire 4 # data2 [3:0] $end
$upscope $end
$upscope $end
$scope module tb_case1 $end
$scope module U0 $end
$var wire 4 $ data3 [3:0] $end
$upscope $end
$upscope $end
$scope module tb_case1 $end
$scope module U0 $end
$var wire 4 % data4 [3:0] $end
$upscope $end
$upscope $end
$scope module tb_case1 $end
$scope module U0 $end
$var wire 4 & data5 [3:0] $end
$upscope $end
$upscope $end
$scope module tb_case1 $end
$scope module U0 $end
$var wire 3 ' sel [2:0] $end
$upscope $end
$upscope $end
$scope module tb_case1 $end
$scope module U0 $end
$var reg 4 ( out [3:0] $end
$upscope $end
$upscope $end
$enddefinitions $end
#0
$dumpvars
b1000 (
b0 '
b1101 &
b1100 %
b1011 $
b1010 #
b1001 "
b1000 !
$end
#5
b1001 (
b1 '
#10
b1010 (
b10 '
#15
b1011 (
b11 '
#20
b1100 (
b100 '
#25
b1101 (
b101 '
#30
b0 (
b110 '
#35
b111 '
