头歌答案/组合逻辑电路设计/运算器/fulladder/fulladder.v
module fulladder(
    input   A,
    input   B,
    input   Cin,
    output  S,
    output  Cout
);

	// 代码量预计2行
    assign S    = A ^ B ^ Cin;
    assign Cout = (A & B) | ((A ^ B) & Cin);

endmodule

头歌答案/组合逻辑电路设计/运算器/fulladder/tb_fulladder.v
`timescale 1ns/1ns

module tb_fulladder();

	reg 	A, B, Cin;
	wire 	S, Cout;

	fulladder U0(.A(A), .B(B), .Cin(Cin), .S(S), .Cout(Cout));

	int i;

	initial begin

		for(i = 0; i < 8; i = i+1) begin
			
			{A, B, Cin} = i;
			#5;

		end
		#5 $finish;
	end

	initial begin
    
        $timeformat(-9, 0, "ns", 5);
        $monitor("At time %t: A = %b, B = %b, Cin = %b, S = %b, Cout = %b", $time, A, B, Cin, S, Cout);
    
    end

    initial begin

		$dumpfile("waveform.vcd");
		$dumpvars(1, tb_fulladder.U0.A);
		$dumpvars(1, tb_fulladder.U0.B);
		$dumpvars(1, tb_fulladder.U0.Cin);
		$dumpvars(1, tb_fulladder.U0.S);
		$dumpvars(1, tb_fulladder.U0.Cout);

    end

endmodule // tb_fulladder

头歌答案/组合逻辑电路设计/运算器/fulladder/waveform.vcd
$date
	Sun Jan  9 14:38:28 2022
$end
$version
	Icarus Verilog
$end
$timescale
	1ns
$end
$scope module tb_fulladder $end
$scope module U0 $end
$var wire 1 ! A $end
$upscope $end
$upscope $end
$scope module tb_fulladder $end
$scope module U0 $end
$var wire 1 " B $end
$upscope $end
$upscope $end
$scope module tb_fulladder $end
$scope module U0 $end
$var wire 1 # Cin $end
$upscope $end
$upscope $end
$scope module tb_fulladder $end
$scope module U0 $end
$var wire 1 $ S $end
$upscope $end
$upscope $end
$scope module tb_fulladder $end
$scope module U0 $end
$var wire 1 % Cout $end
$upscope $end
$upscope $end
$enddefinitions $end
#0
$dumpvars
0%
0$
0#
0"
0!
$end
#5
1$
1#
#10
1$
1"
0#
#15
1%
0$
1#
#20
0%
1$
1!
0"
0#
#25
1%
0$
1#
#30
0$
1"
0#
#35
1$
1#
