头歌答案/时序逻辑电路设计/触发器和寄存器/dff/dff.v
module dff(
    input   sys_clk,
    input   D,
    output  Q
);

	// 代码量预计3行
    reg Q;

    always @(posedge sys_clk)

        Q <= D;


endmodule

头歌答案/时序逻辑电路设计/触发器和寄存器/dff/tb_dff.v
`timescale 1ns/1ns

`define CLK_PERIOD 10

module tb_dff();

	reg		sys_clk;
    reg		D;
    wire	Q;

    initial begin
    
        sys_clk     <= 1'b0;
        D           <= 1'b0;
    
    end
    
    dff U0(.sys_clk(sys_clk), .D(D), .Q(Q));
    
    always #(`CLK_PERIOD/2) sys_clk = ~sys_clk;
    
    initial begin

    	repeat(5) @(posedge sys_clk);
        	D <= 1'b1;
        repeat(3) @(posedge sys_clk);
        	D <= 1'b0;
        repeat(5) @(posedge sys_clk);
        	D <= 1'b1;
        repeat(3) @(posedge sys_clk);
        	$finish;
                
    
    end

    initial begin
    
        $timeformat(-9, 0, "ns", 5);
        $monitor("At time %t: D = %b, Q = %b", $time, D, Q);
    
    end

    initial begin

		$dumpfile("waveform.vcd");
		$dumpvars(1, tb_dff.U0.sys_clk);
		$dumpvars(1, tb_dff.U0.D);
		$dumpvars(1, tb_dff.U0.Q);

    end

endmodule // tb_dff

头歌答案/时序逻辑电路设计/触发器和寄存器/dff/waveform.vcd
$date
	Mon Jan 10 11:00:35 2022
$end
$version
	Icarus Verilog
$end
$timescale
	1ns
$end
$scope module tb_dff $end
$scope module U0 $end
$var wire 1 ! sys_clk $end
$upscope $end
$upscope $end
$scope module tb_dff $end
$scope module U0 $end
$var wire 1 " D $end
$upscope $end
$upscope $end
$scope module tb_dff $end
$scope module U0 $end
$var reg 1 # Q $end
$upscope $end
$upscope $end
$enddefinitions $end
#0
$dumpvars
x#
0"
0!
$end
#5
0#
1!
#10
0!
#15
1!
#20
0!
#25
1!
#30
0!
#35
1!
#40
0!
#45
1"
1!
#50
0!
#55
1#
1!
#60
0!
#65
1!
#70
0!
#75
0"
1!
#80
0!
#85
0#
1!
#90
0!
#95
1!
#100
0!
#105
1!
#110
0!
#115
1!
#120
0!
#125
1"
1!
#130
0!
#135
1#
1!
