头歌答案/组合逻辑电路设计/卡诺图/Kmap4/Kmap4.v
module Kmap4(
    input   a,
    input   b,
    input   c,
    input   d,
    output  out
);

	// 代码量预计1行
    assign out = (~a & b & ~c & ~d) | (a & ~b & ~c & ~d) | (~a & ~b & ~c & d) | (a & b & ~c & d) | (~a & b & c & d) | (a & ~b & c & d) | (~a & ~b & c & ~d) | (a & b & c & ~d);

endmodule

头歌答案/组合逻辑电路设计/卡诺图/Kmap4/tb_Kmap4.v
`timescale 1ns/1ns

module tb_Kmap4();

	reg 	a, b, c, d;
	wire 	out;

	Kmap4 U0(.a(a), .b(b), .c(c), .d(d), .out(out));

	int i;

	initial begin

		for(i = 0; i < 16; i = i+1) begin
			
			{a, b, c, d} = i;
			#5;

		end
		#5 $finish;
	end

	initial begin
    
        $timeformat(-9, 0, "ns", 5);
        $monitor("At time %t: a = %b, b = %b, c = %b, d = %b, out = %b", $time, a, b, c, d, out);
    
    end

    initial begin

		$dumpfile("waveform.vcd");
		$dumpvars(1, tb_Kmap4.U0.a);
		$dumpvars(1, tb_Kmap4.U0.b);
		$dumpvars(1, tb_Kmap4.U0.c);
		$dumpvars(1, tb_Kmap4.U0.d);
		$dumpvars(1, tb_Kmap4.U0.out);

    end

endmodule // tb_Kmap4

头歌答案/组合逻辑电路设计/卡诺图/Kmap4/waveform.vcd
$date
	Sun Jan  9 21:10:49 2022
$end
$version
	Icarus Verilog
$end
$timescale
	1ns
$end
$scope module tb_Kmap4 $end
$scope module U0 $end
$var wire 1 ! a $end
$upscope $end
$upscope $end
$scope module tb_Kmap4 $end
$scope module U0 $end
$var wire 1 " b $end
$upscope $end
$upscope $end
$scope module tb_Kmap4 $end
$scope module U0 $end
$var wire 1 # c $end
$upscope $end
$upscope $end
$scope module tb_Kmap4 $end
$scope module U0 $end
$var wire 1 $ d $end
$upscope $end
$upscope $end
$scope module tb_Kmap4 $end
$scope module U0 $end
$var wire 1 % out $end
$upscope $end
$upscope $end
$enddefinitions $end
#0
$dumpvars
0%
0$
0#
0"
0!
$end
#5
1%
1$
#10
1#
0$
#15
0%
1$
#20
1%
1"
0#
0$
#25
0%
1$
#30
0%
1#
0$
#35
1%
1$
#40
1%
1!
0"
0#
0$
#45
0%
1$
#50
0%
1#
0$
#55
1%
1$
#60
0%
1"
0#
0$
#65
1%
1$
#70
1#
0$
#75
0%
1$
