头歌答案/时序逻辑电路设计/触发器和寄存器/dff_en/dff_en.v
module dff_en(
    input   sys_clk,
    input   sys_rst_n,
    input   en,
    input   D,
    output  Q
);

	// 代码量预计5~6行
    reg Q;

    always @(posedge sys_clk) begin
    
        if (~sys_rst_n)   Q <= 0;
        else if (en)    Q <= D;
        else            Q <= Q;
    
    end


endmodule

头歌答案/时序逻辑电路设计/触发器和寄存器/dff_en/tb_dff_en.v
`timescale 1ns/1ns

`define CLK_PERIOD 10

module tb_dff_en();

	reg		sys_clk, sys_rst_n;
    reg     en;
    reg		D;
    wire	Q;
    
    dff_en U0(.sys_clk(sys_clk), .sys_rst_n(sys_rst_n), .en(en), .D(D), .Q(Q));
    
    always #(`CLK_PERIOD/2) sys_clk = ~sys_clk;

    initial begin
    
        sys_clk     <= 1'b0;
        sys_rst_n   <= 1'b0;
        en          <= 1'b0;
        D           <= 1'b0;
        #20;
        sys_rst_n   <= 1'b1;
        #20;
        en          <= 1'b1;
    
    end
    
    initial begin

    	repeat(3) @(posedge sys_clk);
        	D <= 1'b1;
        repeat(2) @(posedge sys_clk);
        	D <= 1'b0;
        repeat(3) @(posedge sys_clk);
        	D <= 1'b1;
        repeat(2) @(posedge sys_clk);
            en <= 1'b0;
        repeat(2) @(posedge sys_clk);
            $finish;                
    
    end

    initial begin
    
        $timeformat(-9, 0, "ns", 5);
        $monitor("At time %t: sys_rst_n = %b, en = %b, D = %b, Q = %b", $time, sys_rst_n, en, D, Q);
    
    end

    initial begin

		$dumpfile("waveform.vcd");
		$dumpvars(1, tb_dff_en.U0.sys_clk);
        $dumpvars(1, tb_dff_en.U0.sys_rst_n);
        $dumpvars(1, tb_dff_en.U0.en);
		$dumpvars(1, tb_dff_en.U0.D);
		$dumpvars(1, tb_dff_en.U0.Q);

    end

endmodule // tb_dff_en

头歌答案/时序逻辑电路设计/触发器和寄存器/dff_en/waveform.vcd
$date
	Mon Jan 10 11:41:50 2022
$end
$version
	Icarus Verilog
$end
$timescale
	1ns
$end
$scope module tb_dff_en $end
$scope module U0 $end
$var wire 1 ! sys_clk $end
$upscope $end
$upscope $end
$scope module tb_dff_en $end
$scope module U0 $end
$var wire 1 " sys_rst_n $end
$upscope $end
$upscope $end
$scope module tb_dff_en $end
$scope module U0 $end
$var wire 1 # en $end
$upscope $end
$upscope $end
$scope module tb_dff_en $end
$scope module U0 $end
$var wire 1 $ D $end
$upscope $end
$upscope $end
$scope module tb_dff_en $end
$scope module U0 $end
$var reg 1 % Q $end
$upscope $end
$upscope $end
$enddefinitions $end
#0
$dumpvars
x%
0$
0#
0"
0!
$end
#5
0%
1!
#10
0!
#15
1!
#20
1"
0!
#25
1$
1!
#30
0!
#35
1!
#40
1#
0!
#45
1%
0$
1!
#50
0!
#55
0%
1!
#60
0!
#65
1!
#70
0!
#75
1$
1!
#80
0!
#85
1%
1!
#90
0!
#95
0#
1!
