头歌答案/硬件描述语言基础/层次结构/mod_pos/mod_a.sv
module mod_a (
	input 	a, b, c, d,
	output	out1, out2
);

	assign out1 = a & b;
	assign out2 = c | d;

endmodule

头歌答案/硬件描述语言基础/层次结构/mod_name/mod_name.sv
module mod_name (
	input 	a, b, c, d,
	output	out1, out2
);

	// 代码量预计1行
	mod_a DUT(.a(a), .b(b), .c(c), .d(d), .out1(out1), .out2(out2));

endmodule

头歌答案/硬件描述语言基础/层次结构/mod_name/tb_mod_name.sv
`timescale 1ns/1ns

module tb_mod_name();

	logic 	a, b, c, d;
	logic 	out1, out2;
	
	/*** Verilog HDL Code ***/
	/*reg 	a, b, c, d;
	wire 	out1, out2;*/

	mod_name U0(.a(a), .b(b), .c(c), .d(d), .out1(out1), .out2(out2));

	int i;

	initial begin
		for (int i = 0; i < 16; i++) begin
			{a, b, c, d} = i;
			#5;
		end
		#5 $finish;
	end

	initial begin
    
        $timeformat(-9, 0, "ns", 5);
        $monitor("At time %t: a = %b, b = %b, c = %b, d = %b, out1 = %b, out2 = %b", $time, a, b, c, d, out1, out2);
    
    end

    initial begin

		$dumpfile("waveform.vcd");
		$dumpvars(1, tb_mod_name.U0.a);
		$dumpvars(1, tb_mod_name.U0.b);
		$dumpvars(1, tb_mod_name.U0.c);
		$dumpvars(1, tb_mod_name.U0.d);
		$dumpvars(1, tb_mod_name.U0.out1);
		$dumpvars(1, tb_mod_name.U0.out2);

    end

endmodule // tb_mod_name

头歌答案/硬件描述语言基础/层次结构/mod_name/waveform.vcd
$date
	Thu Dec 16 16:30:25 2021
$end
$version
	Icarus Verilog
$end
$timescale
	1ns
$end
$scope module tb_mod_name $end
$scope module U0 $end
$var wire 1 ! a $end
$upscope $end
$upscope $end
$scope module tb_mod_name $end
$scope module U0 $end
$var wire 1 " b $end
$upscope $end
$upscope $end
$scope module tb_mod_name $end
$scope module U0 $end
$var wire 1 # c $end
$upscope $end
$upscope $end
$scope module tb_mod_name $end
$scope module U0 $end
$var wire 1 $ d $end
$upscope $end
$upscope $end
$scope module tb_mod_name $end
$scope module U0 $end
$var wire 1 % out1 $end
$upscope $end
$upscope $end
$scope module tb_mod_name $end
$scope module U0 $end
$var wire 1 & out2 $end
$upscope $end
$upscope $end
$enddefinitions $end
#0
$dumpvars
0&
0%
0$
0#
0"
0!
$end
#5
1&
1$
#10
1#
0$
#15
1$
#20
0&
1"
0#
0$
#25
1&
1$
#30
1#
0$
#35
1$
#40
0&
1!
0"
0#
0$
#45
1&
1$
#50
1#
0$
#55
1$
#60
1%
0&
1"
0#
0$
#65
1&
1$
#70
1#
0$
#75
1$
