头歌答案/组合逻辑电路设计/多路选择器/mux8_4bits/mux8_4bits.v
module mux8_4bits(
    input   [3 : 0]     D0,
    input   [3 : 0]     D1,
    input   [3 : 0]     D2,
    input   [3 : 0]     D3,
    input   [3 : 0]     D4,
    input   [3 : 0]     D5,
    input   [3 : 0]     D6,
    input   [3 : 0]     D7,
    input   [2 : 0]     sel,
    output  [3 : 0]     Y
);

	// 代码量预计13行
    reg [3 : 0] Y;

    always @(*) begin

        case(sel)
            3'b000 : Y = D0;
            3'b001 : Y = D1;
            3'b010 : Y = D2;
            3'b011 : Y = D3;
            3'b100 : Y = D4;
            3'b101 : Y = D5;
            3'b110 : Y = D6;
            3'b111 : Y = D7; 
        endcase
    end

endmodule

头歌答案/组合逻辑电路设计/多路选择器/mux8_4bits/tb_mux8_4bits.v
`timescale 1ns/1ns

module tb_mux8_4bits();

	reg 	[3 : 0]	D0, D1, D2, D3, D4, D5, D6, D7;
	reg 	[2 : 0]	sel;
	wire 	[3 : 0]	Y;

	mux8_4bits U0(.D0(D0), .D1(D1), .D2(D2), .D3(D3), .D4(D4), .D5(D5), .D6(D6), .D7(D7), .sel(sel), .Y(Y));

	int i;

	initial begin

		D0 = 4'h6;
		D1 = 4'hB;
		D2 = 4'h2;
		D3 = 4'h7;
		D4 = 4'h8;
		D5 = 4'hF;
		D6 = 4'hC;
		D7 = 4'hA;

		for (int i = 0; i < 8; i++) begin
			sel = i;
			#5;
		end
		#5 $finish;
	end

	initial begin
    
        $timeformat(-9, 0, "ns", 5);
        $monitor("At time %t: D0 = 0x%x, D1 = 0x%x, D2 = 0x%x, D3 = 0x%x, D4 = 0x%x, D5 = 0x%x, D6 = 0x%x, D7 = 0x%x, sel = %b, Y = %b", $time, D0, D1, D2, D3, D4, D5, D6, D7, sel, Y);
    
    end

    initial begin

		$dumpfile("waveform.vcd");
		$dumpvars(1, tb_mux8_4bits.U0.D0);
		$dumpvars(1, tb_mux8_4bits.U0.D1);
		$dumpvars(1, tb_mux8_4bits.U0.D2);
		$dumpvars(1, tb_mux8_4bits.U0.D3);
		$dumpvars(1, tb_mux8_4bits.U0.D4);
		$dumpvars(1, tb_mux8_4bits.U0.D5);
		$dumpvars(1, tb_mux8_4bits.U0.D6);
		$dumpvars(1, tb_mux8_4bits.U0.D7);
		$dumpvars(1, tb_mux8_4bits.U0.sel);
		$dumpvars(1, tb_mux8_4bits.U0.Y);

    end

endmodule // tb_mux8_4bits

头歌答案/组合逻辑电路设计/多路选择器/mux8_4bits/waveform.vcd
$date
	Fri Jan  7 16:01:10 2022
$end
$version
	Icarus Verilog
$end
$timescale
	1ns
$end
$scope module tb_mux8_4bits $end
$scope module U0 $end
$var wire 4 ! D0 [3:0] $end
$upscope $end
$upscope $end
$scope module tb_mux8_4bits $end
$scope module U0 $end
$var wire 4 " D1 [3:0] $end
$upscope $end
$upscope $end
$scope module tb_mux8_4bits $end
$scope module U0 $end
$var wire 4 # D2 [3:0] $end
$upscope $end
$upscope $end
$scope module tb_mux8_4bits $end
$scope module U0 $end
$var wire 4 $ D3 [3:0] $end
$upscope $end
$upscope $end
$scope module tb_mux8_4bits $end
$scope module U0 $end
$var wire 4 % D4 [3:0] $end
$upscope $end
$upscope $end
$scope module tb_mux8_4bits $end
$scope module U0 $end
$var wire 4 & D5 [3:0] $end
$upscope $end
$upscope $end
$scope module tb_mux8_4bits $end
$scope module U0 $end
$var wire 4 ' D6 [3:0] $end
$upscope $end
$upscope $end
$scope module tb_mux8_4bits $end
$scope module U0 $end
$var wire 4 ( D7 [3:0] $end
$upscope $end
$upscope $end
$scope module tb_mux8_4bits $end
$scope module U0 $end
$var wire 3 ) sel [2:0] $end
$upscope $end
$upscope $end
$scope module tb_mux8_4bits $end
$scope module U0 $end
$var reg 4 * Y [3:0] $end
$upscope $end
$upscope $end
$enddefinitions $end
#0
$dumpvars
b110 *
b0 )
b1010 (
b1100 '
b1111 &
b1000 %
b111 $
b10 #
b1011 "
b110 !
$end
#5
b1011 *
b1 )
#10
b10 *
b10 )
#15
b111 *
b11 )
#20
b1000 *
b100 )
#25
b1111 *
b101 )
#30
b1100 *
b110 )
#35
b1010 *
b111 )
