头歌答案/时序逻辑电路设计/有限状态机/fsm6/fsm6.v
module fsm6(
    input   sys_clk,
    input   sys_rst_n,
    input   in,
    output  out
);

	// 代码量预计25行
    localparam S0 = 2'b00, S1 = 2'b01, S2 = 2'b10, S3 = 2'b11;

    reg out;
    reg [1 : 0] cstate, nstate;

    always @(posedge sys_clk) begin
    
        if (~sys_rst_n) cstate <= S0;
        else            cstate <= nstate;
    
    end

    always @(*) begin
        case(cstate)
            S0  :   if (in == 0) nstate = S0;
                    else nstate = S1;
            S1  :   if (in == 0) nstate = S0;
                    else nstate = S2;
            S2  :   if (in == 0) nstate = S3;
                    else nstate = S2;
            S3  :   if (in == 0) nstate = S0;
                    else nstate = S1;
            default :   nstate = S0;
        endcase
    end

    always @(posedge sys_clk) begin
    
        if (~sys_rst_n) out <= 0;
        else if ((cstate == S3) && (in == 1)) out <= 1;
        else    out <= 0;
    
    end


endmodule

头歌答案/时序逻辑电路设计/有限状态机/fsm6/tb_fsm6.v
`timescale 1ns/1ns

`define CLK_PERIOD 10

module tb_fsm6();

	reg		sys_clk, sys_rst_n;
    reg     in;
    wire	out;

    fsm6 U0(
        .sys_clk(sys_clk),
        .sys_rst_n(sys_rst_n),
        .in(in),
        .out(out)
    );

    int i;
    reg [7 : 0] testvec;

    initial begin
    
        sys_clk     <= 1'b0;
        sys_rst_n   <= 1'b0;
        in          <= 1'b0;
        testvec     <= 8'b11011010;
        #20;
        sys_rst_n   <= 1'b1;
    
    end
    
    always #(`CLK_PERIOD/2) sys_clk = ~sys_clk;
    
    initial begin

        @(posedge sys_rst_n);
        for (int i = 7; i >= 0; i--) begin
            @(posedge sys_clk);
            in <= testvec[i];
        end
        @(posedge sys_clk);
        $finish;
                
    
    end

    initial begin
    
        $timeformat(-9, 0, "ns", 5);
        $monitor("At time %t: sys_rst_n = %b, in = %b, cstate = %b, nstate = %b, out = %b", $time, sys_rst_n, in, tb_fsm6.U0.cstate, tb_fsm6.U0.nstate, out);
    
    end

    initial begin

		$dumpfile("waveform.vcd");
		$dumpvars(1, tb_fsm6.U0.sys_clk);
		$dumpvars(1, tb_fsm6.U0.sys_rst_n);
		$dumpvars(1, tb_fsm6.U0.in);
        $dumpvars(1, tb_fsm6.U0.cstate);
        $dumpvars(1, tb_fsm6.U0.nstate);
        $dumpvars(1, tb_fsm6.U0.out);

    end

endmodule // tb_fsm6

头歌答案/时序逻辑电路设计/有限状态机/fsm6/waveform.vcd
$date
	Fri Jan 14 20:58:01 2022
$end
$version
	Icarus Verilog
$end
$timescale
	1ns
$end
$scope module tb_fsm6 $end
$scope module U0 $end
$var wire 1 ! sys_clk $end
$upscope $end
$upscope $end
$scope module tb_fsm6 $end
$scope module U0 $end
$var wire 1 " sys_rst_n $end
$upscope $end
$upscope $end
$scope module tb_fsm6 $end
$scope module U0 $end
$var wire 1 # in $end
$upscope $end
$upscope $end
$scope module tb_fsm6 $end
$scope module U0 $end
$var reg 2 $ cstate [1:0] $end
$upscope $end
$upscope $end
$scope module tb_fsm6 $end
$scope module U0 $end
$var reg 2 % nstate [1:0] $end
$upscope $end
$upscope $end
$scope module tb_fsm6 $end
$scope module U0 $end
$var reg 1 & out $end
$upscope $end
$upscope $end
$enddefinitions $end
#0
$dumpvars
x&
b0 %
bx $
0#
0"
0!
$end
#5
b0 $
0&
1!
#10
0!
#15
1!
#20
1"
0!
#25
b1 %
1#
1!
#30
0!
#35
b10 %
b1 $
1!
#40
0!
#45
b11 %
b10 $
0#
1!
#50
0!
#55
b1 %
1#
b11 $
1!
#60
0!
#65
b10 %
b1 $
1&
1!
#70
0!
#75
b11 %
0#
0&
b10 $
1!
#80
0!
#85
b1 %
b11 $
1#
1!
#90
0!
#95
b0 %
0#
1&
b1 $
1!
#100
0!
#105
b0 $
0&
1!
