头歌答案/组合逻辑电路设计/多路选择器/mux256/mux256.v
module mux256(
    input   [255 : 0] D,
    input   [  7 : 0] sel,
    output            Y
);

	// 代码量预计1行
    assign Y = D[sel];

endmodule

头歌答案/组合逻辑电路设计/多路选择器/mux256/tb_mux256.v
`timescale 1ns/1ns

module tb_mux256();

	reg 	[255 : 0]	D;
	reg 	[  7 : 0]	sel;
	wire 				Y;

	mux256 U0(.D(D), .sel(sel), .Y(Y));

	int i;

	initial begin

		D = 256'hABCD;

		for (int i = 0; i < 16; i++) begin
			sel = i;
			#5;
		end
		#5 $finish;
	end

	initial begin
    
        $timeformat(-9, 0, "ns", 5);
        $monitor("At time %t: D = 0x%4H, sel = %b, Y = %b", $time, D, sel, Y);
    
    end

    initial begin

		$dumpfile("waveform.vcd");
		$dumpvars(1, tb_mux256.U0.D);
		$dumpvars(1, tb_mux256.U0.sel);
		$dumpvars(1, tb_mux256.U0.Y);

    end

endmodule // tb_mux256

头歌答案/组合逻辑电路设计/多路选择器/mux256/waveform.vcd
$date
	Fri Jan  7 16:46:26 2022
$end
$version
	Icarus Verilog
$end
$timescale
	1ns
$end
$scope module tb_mux256 $end
$scope module U0 $end
$var wire 256 ! D [255:0] $end
$upscope $end
$upscope $end
$scope module tb_mux256 $end
$scope module U0 $end
$var wire 8 " sel [7:0] $end
$upscope $end
$upscope $end
$scope module tb_mux256 $end
$scope module U0 $end
$var wire 1 # Y $end
$upscope $end
$upscope $end
$enddefinitions $end
#0
$dumpvars
1#
b0 "
b1010101111001101 !
$end
#5
0#
b1 "
#10
1#
b10 "
#15
b11 "
#20
0#
b100 "
#25
b101 "
#30
1#
b110 "
#35
b111 "
#40
b1000 "
#45
b1001 "
#50
0#
b1010 "
#55
1#
b1011 "
#60
0#
b1100 "
#65
1#
b1101 "
#70
0#
b1110 "
#75
1#
b1111 "
