头歌答案/时序逻辑电路设计/有限状态机/Lemmings2/Lemmings2.v
module Lemmings2(
    input   sys_clk,
    input   sys_rst_n,
    input   bump_left,
    input   bump_right,
    input   ground,
    output  walk_left,
    output  walk_right,
    output  aaah
);

	// 代码量预计22行
    localparam LEFT=2'b00, FALL_L = 2'b01, RIGHT=2'b10, FALL_R = 2'b11;

    reg         walk_left, walk_right, aaah;
    reg [1 : 0] cstate, nstate;

    always @(posedge sys_clk) begin
    
        if (~sys_rst_n) cstate <= LEFT;
        else            cstate <= nstate;
    
    end

    always @(*) begin
        case (cstate)
            LEFT:
                if (ground) nstate = (bump_left)? RIGHT : LEFT;
                else        nstate = FALL_L;
            RIGHT:
                if (ground) nstate = (bump_right)? LEFT : RIGHT;
                else        nstate = FALL_R;
            FALL_L: nstate = (ground)? LEFT  : cstate;
            FALL_R: nstate = (ground)? RIGHT : cstate;
        endcase
    end

    assign walk_left    = (cstate == LEFT);
    assign walk_right   = (cstate == RIGHT);
    assign aaah         = (cstate == FALL_L) || (cstate == FALL_R);


endmodule

头歌答案/时序逻辑电路设计/有限状态机/Lemmings2/tb_Lemmings2.v
`timescale 1ns/1ns

`define CLK_PERIOD 10

module tb_Lemmings2();

	reg		sys_clk, sys_rst_n;
    reg     bump_left, bump_right, ground;
    wire	walk_left, walk_right, aaah;

    Lemmings2 U0(
        .sys_clk(sys_clk),
        .sys_rst_n(sys_rst_n),
        .bump_left(bump_left),
        .bump_right(bump_right),
        .ground(ground),
        .walk_left(walk_left),
        .walk_right(walk_right),
        .aaah(aaah)
    );

    initial begin
    
        sys_clk     <= 1'b0;
        sys_rst_n   <= 1'b0;
        bump_left   <= 1'b0;
        bump_right  <= 1'b0;
        ground      <= 1'b1;
        #20;
        sys_rst_n   <= 1'b1;
    
    end
    
    always #(`CLK_PERIOD/2) sys_clk = ~sys_clk;
    
    initial begin

        @(posedge sys_rst_n);
        @(posedge sys_clk);
        {bump_left, bump_right, ground} <= 3'b000;
        @(posedge sys_clk);
        {bump_left, bump_right, ground} <= 3'b010;
        @(posedge sys_clk);
        {bump_left, bump_right, ground} <= 3'b100;
        @(posedge sys_clk);
        {bump_left, bump_right, ground} <= 3'b001;
        @(posedge sys_clk);
        {bump_left, bump_right, ground} <= 3'b101;
        @(posedge sys_clk);
        {bump_left, bump_right, ground} <= 3'b011;
        @(posedge sys_clk);
        {bump_left, bump_right, ground} <= 3'b111;
        @(posedge sys_clk);
        {bump_left, bump_right, ground} <= 3'b110;
        @(posedge sys_clk);
        {bump_left, bump_right, ground} <= 3'b001;
        repeat (2) @(posedge sys_clk);
        $finish;
                
    
    end

    initial begin
    
        $timeformat(-9, 0, "ns", 5);
        $monitor("At time %t: sys_rst_n = %b, bump_left = %b, bump_right = %b, ground = %b, cstate = %b, nstate = %b, walk_left = %b, walk_right = %b, aaah = %b", $time, sys_rst_n, bump_left, bump_right, ground, tb_Lemmings2.U0.cstate, tb_Lemmings2.U0.nstate, walk_left, walk_right, aaah);
    
    end

    initial begin

		$dumpfile("waveform.vcd");
		$dumpvars(1, tb_Lemmings2.U0.sys_clk);
		$dumpvars(1, tb_Lemmings2.U0.sys_rst_n);
		$dumpvars(1, tb_Lemmings2.U0.bump_left);
        $dumpvars(1, tb_Lemmings2.U0.bump_right);
        $dumpvars(1, tb_Lemmings2.U0.ground);
        $dumpvars(1, tb_Lemmings2.U0.cstate);
        $dumpvars(1, tb_Lemmings2.U0.nstate);
        $dumpvars(1, tb_Lemmings2.U0.walk_left);
        $dumpvars(1, tb_Lemmings2.U0.walk_right);
        $dumpvars(1, tb_Lemmings2.U0.aaah);

    end

endmodule // tb_Lemmings2

头歌答案/时序逻辑电路设计/有限状态机/Lemmings2/waveform.vcd
$date
	Sun Jan 16 10:39:51 2022
$end
$version
	Icarus Verilog
$end
$timescale
	1ns
$end
$scope module tb_Lemmings2 $end
$scope module U0 $end
$var wire 1 ! sys_clk $end
$upscope $end
$upscope $end
$scope module tb_Lemmings2 $end
$scope module U0 $end
$var wire 1 " sys_rst_n $end
$upscope $end
$upscope $end
$scope module tb_Lemmings2 $end
$scope module U0 $end
$var wire 1 # bump_left $end
$upscope $end
$upscope $end
$scope module tb_Lemmings2 $end
$scope module U0 $end
$var wire 1 $ bump_right $end
$upscope $end
$upscope $end
$scope module tb_Lemmings2 $end
$scope module U0 $end
$var wire 1 % ground $end
$upscope $end
$upscope $end
$scope module tb_Lemmings2 $end
$scope module U0 $end
$var reg 2 & cstate [1:0] $end
$upscope $end
$upscope $end
$scope module tb_Lemmings2 $end
$scope module U0 $end
$var reg 2 ' nstate [1:0] $end
$upscope $end
$upscope $end
$scope module tb_Lemmings2 $end
$scope module U0 $end
$var wire 1 ( walk_left $end
$upscope $end
$upscope $end
$scope module tb_Lemmings2 $end
$scope module U0 $end
$var wire 1 ) walk_right $end
$upscope $end
$upscope $end
$scope module tb_Lemmings2 $end
$scope module U0 $end
$var wire 1 * aaah $end
$upscope $end
$upscope $end
$enddefinitions $end
#0
$dumpvars
x*
x)
x(
bx '
bx &
1%
0$
0#
0"
0!
$end
#5
b0 '
0*
1(
0)
b0 &
1!
#10
0!
#15
1!
#20
1"
0!
#25
b1 '
0%
1!
#30
0!
#35
1*
1$
0(
b1 &
1!
#40
0!
#45
1#
0$
1!
#50
0!
#55
b0 '
0#
1%
1!
#60
0!
#65
0*
b10 '
1(
b0 &
1#
1!
#70
0!
#75
b0 '
0#
1$
0(
1)
b10 &
1!
#80
0!
#85
b10 '
1(
0)
b0 &
1#
1!
#90
0!
#95
b11 '
0%
0(
1)
b10 &
1!
#100
0!
#105
1*
b10 '
0)
b11 &
0#
0$
1%
1!
#110
0!
#115
0*
1)
b10 &
1!
