头歌答案/硬件描述语言基础/过程块/alif1/alif1.sv
`timescale 1ns/1ns

module alif1(
    input 	a,
    input 	b,
    input 	sel_b1,
    input 	sel_b2,
    output 	out_assign,
    output 	out_alwaysblock   ); 
    
	//预计代码量6-7行
	reg out_alwaysblock;
    assign out_assign = ({sel_b1, sel_b2} == 2'b11)? b : a;
    
    always @(*) begin
        if({sel_b1, sel_b2} == 2'b11) out_alwaysblock = b;
        else out_alwaysblock = a;
    end

endmodule

头歌答案/硬件描述语言基础/过程块/alif1/tb_alif1.sv
`timescale 1ns/1ns

module tb_alif1();

	logic 	a, b, sel_b1, sel_b2;
	logic 	out_assign, out_alwaysblock;

	/*** Verilog HDL Code***/
	/*reg 	a, b, sel_b1, sel_b2;
	wire 	out_assign, out_alwaysblock;*/

	alif1 U0(.a(a), .b(b), .sel_b1(sel_b1), .sel_b2(sel_b2), .out_assign(out_assign), .out_alwaysblock(out_alwaysblock));

	initial begin
			a 		= 1'b0;
			b 		= 1'b1;
			sel_b1 	= 1'b0;
			sel_b2 	= 1'b0;
		#5  sel_b1 	= 1'b1;
			sel_b2 	= 1'b0;
		#5  sel_b1 	= 1'b0;
			sel_b2 	= 1'b1;
		#5  sel_b1 	= 1'b1;
			sel_b2 	= 1'b1;
		#5	a 		= 1'b1;
			b 		= 1'b0;
			sel_b1 	= 1'b0;
			sel_b2 	= 1'b0;
		#5  sel_b1 	= 1'b1;
			sel_b2 	= 1'b0;
		#5  sel_b1 	= 1'b0;
			sel_b2 	= 1'b1;
		#5  sel_b1 	= 1'b1;
			sel_b2 	= 1'b1;
		#5 $finish;
	end

	initial begin
    
        $timeformat(-9, 0, "ns", 5);
        $monitor("At time %t: a = %b, b = %b, sel_b1 = %b, sel_b2 = %b, out_assign = %b, out_alwaysblock = %b", $time, a, b, sel_b1, sel_b2, out_assign, out_alwaysblock);
    
    end

    initial begin

		$dumpfile("waveform.vcd");
		$dumpvars(1, tb_alif1.U0.a);
		$dumpvars(1, tb_alif1.U0.b);
		$dumpvars(1, tb_alif1.U0.sel_b1);
		$dumpvars(1, tb_alif1.U0.sel_b2);
		$dumpvars(1, tb_alif1.U0.out_assign);
		$dumpvars(1, tb_alif1.U0.out_alwaysblock);

    end

endmodule // tb_alif1

头歌答案/硬件描述语言基础/过程块/alif1/waveform.vcd
$date
	Thu Dec 16 21:13:18 2021
$end
$version
	Icarus Verilog
$end
$timescale
	1ns
$end
$scope module tb_alif1 $end
$scope module U0 $end
$var wire 1 ! a $end
$upscope $end
$upscope $end
$scope module tb_alif1 $end
$scope module U0 $end
$var wire 1 " b $end
$upscope $end
$upscope $end
$scope module tb_alif1 $end
$scope module U0 $end
$var wire 1 # sel_b1 $end
$upscope $end
$upscope $end
$scope module tb_alif1 $end
$scope module U0 $end
$var wire 1 $ sel_b2 $end
$upscope $end
$upscope $end
$scope module tb_alif1 $end
$scope module U0 $end
$var wire 1 % out_assign $end
$upscope $end
$upscope $end
$scope module tb_alif1 $end
$scope module U0 $end
$var reg 1 & out_alwaysblock $end
$upscope $end
$upscope $end
$enddefinitions $end
#0
$dumpvars
0&
0%
0$
0#
1"
0!
$end
#5
1#
#10
1$
0#
#15
1&
1%
1#
#20
0$
0#
0"
1!
#25
1#
#30
1$
0#
#35
0&
0%
1#
