头歌答案/时序逻辑电路设计/计数器/cnt_ud/cnt_ud.v
module cnt_ud #(parameter N = 4)(
    input                sys_clk,
    input                sys_rst_n,
    input                up,
    output   [N - 1 : 0] cnt
);

	// 代码量预计6行
    reg [N-1 : 0] cnt;

    always @(posedge sys_clk) begin
    
        if (~sys_rst_n) cnt <= 0;
        else if (up)    cnt <= cnt + 1;
        else            cnt <= cnt - 1;
    
    end


endmodule

头歌答案/时序逻辑电路设计/计数器/cnt_ud/tb_cnt_ud.v
`timescale 1ns/1ns

`define CLK_PERIOD 10

module tb_cnt_ud();

	reg		          sys_clk, sys_rst_n;
    reg               up;
    wire	[3 : 0]   cnt;

    cnt_ud U0(
        .sys_clk    (sys_clk),
        .sys_rst_n  (sys_rst_n),
        .up         (up),
        .cnt        (cnt)
    );

    initial begin
    
        sys_clk     <= 1'b0;
        sys_rst_n   <= 1'b0;
        up          <= 1'b1;
        #20;
        sys_rst_n   <= 1'b1;
    
    end
    
    always #(`CLK_PERIOD/2) sys_clk = ~sys_clk;
    
    initial begin

        repeat (10) @(posedge sys_clk);
        up          <= 1'b0;
        repeat (6) @(posedge sys_clk);
        $finish;
    
    end

    initial begin
    
        $timeformat(-9, 0, "ns", 5);
        $monitor("At time %t: sys_rst_n = %b, up = %b, cnt = %b", $time, sys_rst_n, up, cnt);
    
    end

    initial begin

		$dumpfile("waveform.vcd");
		$dumpvars(1, tb_cnt_ud.U0.sys_clk);
		$dumpvars(1, tb_cnt_ud.U0.sys_rst_n);
        $dumpvars(1, tb_cnt_ud.U0.up);
		$dumpvars(1, tb_cnt_ud.U0.cnt);

    end

endmodule // tb_cnt_ud

头歌答案/时序逻辑电路设计/计数器/cnt_ud/waveform.vcd
$date
	Tue Jan 11 09:42:07 2022
$end
$version
	Icarus Verilog
$end
$timescale
	1ns
$end
$scope module tb_cnt_ud $end
$scope module U0 $end
$var wire 1 ! sys_clk $end
$upscope $end
$upscope $end
$scope module tb_cnt_ud $end
$scope module U0 $end
$var wire 1 " sys_rst_n $end
$upscope $end
$upscope $end
$scope module tb_cnt_ud $end
$scope module U0 $end
$var wire 1 # up $end
$upscope $end
$upscope $end
$scope module tb_cnt_ud $end
$scope module U0 $end
$var reg 4 $ cnt [3:0] $end
$upscope $end
$upscope $end
$enddefinitions $end
#0
$dumpvars
bx $
1#
0"
0!
$end
#5
b0 $
1!
#10
0!
#15
1!
#20
1"
0!
#25
b1 $
1!
#30
0!
#35
b10 $
1!
#40
0!
#45
b11 $
1!
#50
0!
#55
b100 $
1!
#60
0!
#65
b101 $
1!
#70
0!
#75
b110 $
1!
#80
0!
#85
b111 $
1!
#90
0!
#95
0#
b1000 $
1!
#100
0!
#105
b111 $
1!
#110
0!
#115
b110 $
1!
#120
0!
#125
b101 $
1!
#130
0!
#135
b100 $
1!
#140
0!
#145
b11 $
1!
#150
0!
#155
b10 $
1!
