头歌答案/组合逻辑电路设计/卡诺图/Kmap1/Kmap1.v
module Kmap1(
    input   a,
    input   b,
    input   c,
    output  out
);

	// 代码量预计1行
    assign out = (a | b | c);

endmodule

头歌答案/组合逻辑电路设计/卡诺图/Kmap1/tb_Kmap1.v
`timescale 1ns/1ns

module tb_Kmap1();

	reg 	a, b, c;
	wire 	out;

	Kmap1 U0(.a(a), .b(b), .c(c), .out(out));

	int i;

	initial begin

		for(i = 0; i < 8; i = i+1) begin
			
			{a, b, c} = i;
			#5;

		end
		#5 $finish;
	end

	initial begin
    
        $timeformat(-9, 0, "ns", 5);
        $monitor("At time %t: a = %b, b = %b, c = %b, out = %b", $time, a, b, c, out);
    
    end

    initial begin

		$dumpfile("waveform.vcd");
		$dumpvars(1, tb_Kmap1.U0.a);
		$dumpvars(1, tb_Kmap1.U0.b);
		$dumpvars(1, tb_Kmap1.U0.c);
		$dumpvars(1, tb_Kmap1.U0.out);

    end

endmodule // tb_Kmap1

头歌答案/组合逻辑电路设计/卡诺图/Kmap1/waveform.vcd
$date
	Sun Jan  9 15:48:59 2022
$end
$version
	Icarus Verilog
$end
$timescale
	1ns
$end
$scope module tb_Kmap1 $end
$scope module U0 $end
$var wire 1 ! a $end
$upscope $end
$upscope $end
$scope module tb_Kmap1 $end
$scope module U0 $end
$var wire 1 " b $end
$upscope $end
$upscope $end
$scope module tb_Kmap1 $end
$scope module U0 $end
$var wire 1 # c $end
$upscope $end
$upscope $end
$scope module tb_Kmap1 $end
$scope module U0 $end
$var wire 1 $ out $end
$upscope $end
$upscope $end
$enddefinitions $end
#0
$dumpvars
0$
0#
0"
0!
$end
#5
1$
1#
#10
1$
1"
0#
#15
1#
#20
1!
0"
0#
#25
1#
#30
1"
0#
#35
1#
